dragonflow/__init__.py
dragonflow/_i18n.py
dragonflow/version.py
dragonflow/cli/__init__.py
dragonflow/cli/df_db.py
dragonflow/cli/utils.py
dragonflow/cmd/__init__.py
dragonflow/cmd/eventlet/__init__.py
dragonflow/cmd/eventlet/df_bgp_service.py
dragonflow/cmd/eventlet/df_l3_agent.py
dragonflow/cmd/eventlet/df_local_controller.py
dragonflow/cmd/eventlet/df_metadata_service.py
dragonflow/cmd/eventlet/df_publisher_service.py
dragonflow/common/__init__.py
dragonflow/common/constants.py
dragonflow/common/dhcp.py
dragonflow/common/exceptions.py
dragonflow/common/extensions.py
dragonflow/common/utils.py
dragonflow/conf/__init__.py
dragonflow/conf/df_active_port_detection.py
dragonflow/conf/df_bgp.py
dragonflow/conf/df_cassandra.py
dragonflow/conf/df_common_params.py
dragonflow/conf/df_dhcp.py
dragonflow/conf/df_dnat.py
dragonflow/conf/df_l2.py
dragonflow/conf/df_l3.py
dragonflow/conf/df_metadata_service.py
dragonflow/conf/df_provider_networks.py
dragonflow/conf/df_ryu.py
dragonflow/conf/df_snat.py
dragonflow/conf/opts.py
dragonflow/controller/__init__.py
dragonflow/controller/df_base_app.py
dragonflow/controller/df_bgp_service.py
dragonflow/controller/df_local_controller.py
dragonflow/controller/df_publisher_service.py
dragonflow/controller/dispatcher.py
dragonflow/controller/port_locator.py
dragonflow/controller/ryu_base_app.py
dragonflow/controller/service.py
dragonflow/controller/topology.py
dragonflow/controller/apps/__init__.py
dragonflow/controller/apps/active_port_detection.py
dragonflow/controller/apps/aging.py
dragonflow/controller/apps/chassis_snat.py
dragonflow/controller/apps/classifier.py
dragonflow/controller/apps/dhcp.py
dragonflow/controller/apps/dnat.py
dragonflow/controller/apps/fc.py
dragonflow/controller/apps/l2.py
dragonflow/controller/apps/l3_base.py
dragonflow/controller/apps/l3_proactive.py
dragonflow/controller/apps/l3_reactive.py
dragonflow/controller/apps/legacy_snat.py
dragonflow-4.0.0.dist-info/DESCRIPTION.rst
dragonflow-4.0.0.dist-info/METADATA
dragonflow-4.0.0.dist-info/RECORD
dragonflow-4.0.0.dist-info/WHEEL
dragonflow-4.0.0.dist-info/entry_points.txt
dragonflow-4.0.0.dist-info/metadata.json
dragonflow-4.0.0.dist-info/pbr.json
dragonflow-4.0.0.dist-info/top_level.txt
