Metadata-Version: 2.0
Name: dragonflow
Version: 4.0.0
Summary: Distributed SDN solution for OpenStack Neutron
Home-page: https://docs.openstack.org/dragonflow/latest/
Author: OpenStack
Author-email: openstack-dev@lists.openstack.org
License: Apache License 2.0
Platform: UNKNOWN
Classifier: Environment :: OpenStack
Classifier: Intended Audience :: Information Technology
Classifier: Intended Audience :: System Administrators
Classifier: License :: OSI Approved :: Apache Software License
Classifier: Operating System :: POSIX :: Linux
Classifier: Programming Language :: Python
Classifier: Programming Language :: Python :: 2
Classifier: Programming Language :: Python :: 2.7
Classifier: Programming Language :: Python :: 3
Classifier: Programming Language :: Python :: 3.5
Requires-Dist: Babel (>=2.3.4,!=2.4.0)
Requires-Dist: SQLAlchemy (>=1.0.10,!=1.1.6,!=1.1.5,!=1.1.8,!=1.1.7)
Requires-Dist: WebOb (>=1.7.1)
Requires-Dist: alembic (>=0.8.10)
Requires-Dist: cassandra-driver (>=2.1.4,!=3.6.0)
Requires-Dist: crc16 (>=0.1.1)
Requires-Dist: etcd3gw (>=0.1.0)
Requires-Dist: httplib2 (>=0.7.5)
Requires-Dist: jsonmodels (>=2.1.3)
Requires-Dist: kazoo (>=2.2)
Requires-Dist: netaddr (!=0.7.16,>=0.7.13)
Requires-Dist: neutron-lib (>=1.9.0)
Requires-Dist: oslo.config (!=4.4.0,>=4.0.0,!=4.3.0)
Requires-Dist: oslo.db (>=4.24.0)
Requires-Dist: oslo.i18n (>=2.1.0,!=3.15.2)
Requires-Dist: oslo.log (>=3.30.0)
Requires-Dist: oslo.reports (>=0.6.0)
Requires-Dist: oslo.serialization (>=1.10.0,!=2.19.1)
Requires-Dist: ovs (>=2.7.0)
Requires-Dist: ovsdbapp (>=0.4.0)
Requires-Dist: pbr (!=2.1.0,>=2.0.0)
Requires-Dist: pyzmq (>=14.3.1)
Requires-Dist: ryu (>=4.14)
Requires-Dist: six (>=1.9.0)
